pyexfil/__init__.py
PyExfil-1.3.dist-info/LICENSE.md
PyExfil-1.3.dist-info/METADATA
PyExfil-1.3.dist-info/WHEEL
PyExfil-1.3.dist-info/top_level.txt
PyExfil-1.3.dist-info/RECORD
